{"_type":"export","__export_format":4,"__export_date":"2024-04-23T14:09:01.198Z","__export_source":"insomnia.desktop.app:v8.6.1","resources":[{"_id":"req_23e36960dcc44bbfbaadfa57f73dfef1","parentId":"wrk_b3981ded01e340478470c2a0d98ea73d","modified":1713880518271,"created":1713879964257,"url":"http://localhost:8080/createRoom","name":"createRoom","description":"","method":"POST","body":{"mimeType":"application/json","text":""},"parameters":[{"id":"pair_988f7783c0ad461f8f19f83d1e88ca59","name":"roomName","value":"Cat room","description":""}],"headers":[{"name":"Content-Type","value":"application/json"},{"name":"User-Agent","value":"insomnia/8.6.1"}],"authentication":{},"metaSortKey":-1713879722697,"isPrivate":false,"pathParameters":[],"settingStoreCookies":true,"settingSendCookies":true,"settingDisableRenderRequestBody":false,"settingEncodeUrl":true,"settingRebuildPath":true,"settingFollowRedirects":"global","_type":"request"},{"_id":"wrk_b3981ded01e340478470c2a0d98ea73d","parentId":null,"modified":1713879265333,"created":1713879265333,"name":"My Collection","description":"","scope":"collection","_type":"workspace"},{"_id":"req_ef0f7a35a60240d596cd7b708655bb02","parentId":"wrk_b3981ded01e340478470c2a0d98ea73d","modified":1713880688894,"created":1713880404647,"url":"http://localhost:8080/sendMessage","name":"sendMessage","description":"","method":"POST","body":{"mimeType":"application/json","text":"{\n\t\"sender\": \"Kočkomil\",\n\t\"messageText\": \"Koťata jsou skvělá\",\n\t\"roomName\": \"Cat room\"\n}"},"parameters":[{"id":"pair_66903933b2ac40f5858503473646b6fb","name":"","value":"","description":""}],"headers":[{"name":"Content-Type","value":"application/json"},{"name":"User-Agent","value":"insomnia/8.6.1"}],"authentication":{},"metaSortKey":-1713879722647,"isPrivate":false,"pathParameters":[],"settingStoreCookies":true,"settingSendCookies":true,"settingDisableRenderRequestBody":false,"settingEncodeUrl":true,"settingRebuildPath":true,"settingFollowRedirects":"global","_type":"request"},{"_id":"req_56bebeeec9d34400a2a512ec5e9e4d7d","parentId":"wrk_b3981ded01e340478470c2a0d98ea73d","modified":1713880525671,"created":1713880261486,"url":"http://localhost:8080/listByRoomName","name":"listByRoomName","description":"","method":"GET","body":{},"parameters":[{"id":"pair_9bc664d314ba4aa99f6c6b4413f8d0b0","name":"roomName","value":"Cat room","description":""}],"headers":[{"name":"User-Agent","value":"insomnia/8.6.1"}],"authentication":{},"metaSortKey":-1713879722622,"isPrivate":false,"pathParameters":[],"settingStoreCookies":true,"settingSendCookies":true,"settingDisableRenderRequestBody":false,"settingEncodeUrl":true,"settingRebuildPath":true,"settingFollowRedirects":"global","_type":"request"},{"_id":"req_6e06195ecd01417aa564d09d8ecce062","parentId":"wrk_b3981ded01e340478470c2a0d98ea73d","modified":1713880138500,"created":1713879722597,"url":"http://localhost:8080/getRoom","name":"getRoom","description":"","method":"GET","body":{},"parameters":[{"id":"pair_9bc664d314ba4aa99f6c6b4413f8d0b0","name":"roomName","value":"Cat room","description":""}],"headers":[{"name":"User-Agent","value":"insomnia/8.6.1"}],"authentication":{},"metaSortKey":-1713879722597,"isPrivate":false,"pathParameters":[],"settingStoreCookies":true,"settingSendCookies":true,"settingDisableRenderRequestBody":false,"settingEncodeUrl":true,"settingRebuildPath":true,"settingFollowRedirects":"global","_type":"request"},{"_id":"req_27c9abacbbb64e319f41619423e44cd6","parentId":"wrk_b3981ded01e340478470c2a0d98ea73d","modified":1713880158105,"created":1713880152196,"url":"http://localhost:8080/listRooms","name":"listRooms","description":"","method":"GET","body":{},"parameters":[],"headers":[{"name":"User-Agent","value":"insomnia/8.6.1"}],"authentication":{},"metaSortKey":-1713879722572,"isPrivate":false,"pathParameters":[],"settingStoreCookies":true,"settingSendCookies":true,"settingDisableRenderRequestBody":false,"settingEncodeUrl":true,"settingRebuildPath":true,"settingFollowRedirects":"global","_type":"request"},{"_id":"env_85f504414c1d0f28f362b037ba327805b4f8f247","parentId":"wrk_b3981ded01e340478470c2a0d98ea73d","modified":1713879265337,"created":1713879265337,"name":"Base Environment","data":{},"dataPropertyOrder":null,"color":null,"isPrivate":false,"metaSortKey":1713879265337,"_type":"environment"},{"_id":"jar_85f504414c1d0f28f362b037ba327805b4f8f247","parentId":"wrk_b3981ded01e340478470c2a0d98ea73d","modified":1713879789630,"created":1713879265340,"name":"Default Jar","cookies":[{"key":"JSESSIONID","value":"23F4C2A51976F543500509B9406FFAFE","domain":"localhost","path":"/","httpOnly":true,"hostOnly":true,"creation":"2024-04-23T13:43:09.629Z","lastAccessed":"2024-04-23T13:43:09.629Z","id":"cf8eac24-b822-4e65-8126-61ee3d028b86"}],"_type":"cookie_jar"}]}